[{"op":"PUSH1","memory":null,"memSize":0,"stack":[],"storage":null},{"op":"PUSH1","memory":null,"memSize":0,"stack":["0x80"],"storage":null},{"op":"MSTORE","memory":null,"memSize":96,"stack":["0x80","0x40"],"storage":null},{"op":"PUSH1","memory":null,"memSize":96,"stack":[],"storage":null},{"op":"CALLDATASIZE","memory":null,"memSize":96,"stack":["0x4"],"storage":null},{"op":"LT","memory":null,"memSize":96,"stack":["0x4","0x4"],"storage":null},{"op":"PUSH2","memory":null,"memSize":96,"stack":["0x0"],"storage":null},{"op":"JUMPI","memory":null,"memSize":96,"stack":["0x0","0x4c"],"storage":null},{"op":"PUSH1","memory":null,"memSize":96,"stack":[],"storage":null},{"op":"CALLDATALOAD","memory":null,"memSize":96,"stack":["0x0"],"storage":null},{"op":"PUSH29","memory":null,"memSize":96,"stack":["0x5fd8c71000000000000000000000000000000000000000000000000000000000"],"storage":null},{"op":"SWAP1","memory":null,"memSize":96,"stack":["0x5fd8c71000000000000000000000000000000000000000000000000000000000","0x100000000000000000000000000000000000000000000000000000000"],"storage":null},{"op":"DIV","memory":null,"memSize":96,"stack":["0x100000000000000000000000000000000000000000000000000000000","0x5fd8c71000000000000000000000000000000000000000000000000000000000"],"storage":null},{"op":"PUSH4","memory":null,"memSize":96,"stack":["0x5fd8c710"],"storage":null},{"op":"AND","memory":null,"memSize":96,"stack":["0x5fd8c710","0xffffffff"],"storage":null},{"op":"DUP1","memory":null,"memSize":96,"stack":["0x5fd8c710"],"storage":null},{"op":"PUSH4","memory":null,"memSize":96,"stack":["0x5fd8c710","0x5fd8c710"],"storage":null},{"op":"EQ","memory":null,"memSize":96,"stack":["0x5fd8c710","0x5fd8c710","0x5fd8c710"],"storage":null},{"op":"PUSH2","memory":null,"memSize":96,"stack":["0x5fd8c710","0x1"],"storage":null},{"op":"JUMPI","memory":null,"memSize":96,"stack":["0x5fd8c710","0x1","0x51"],"storage":null},{"op":"JUMPDEST","memory":null,"memSize":96,"stack":["0x5fd8c710"],"storage":null},{"op":"CALLVALUE","memory":null,"memSize":96,"stack":["0x5fd8c710"],"storage":null},{"op":"DUP1","memory":null,"memSize":96,"stack":["0x5fd8c710","0x0"],"storage":null},{"op":"ISZERO","memory":null,"memSize":96,"stack":["0x5fd8c710","0x0","0x0"],"storage":null},{"op":"PUSH2","memory":null,"memSize":96,"stack":["0x5fd8c710","0x0","0x1"],"storage":null},{"op":"JUMPI","memory":null,"memSize":96,"stack":["0x5fd8c710","0x0","0x1","0x5d"],"storage":null},{"op":"JUMPDEST","memory":null,"memSize":96,"stack":["0x5fd8c710","0x0"],"storage":null},{"op":"POP","memory":null,"memSize":96,"stack":["0x5fd8c710","0x0"],"storage":null},{"op":"PUSH2","memory":null,"memSize":96,"stack":["0x5fd8c710"],"storage":null},{"op":"PUSH2","memory":null,"memSize":96,"stack":["0x5fd8c710","0x66"],"storage":null},{"op":"JUMP","memory":null,"memSize":96,"stack":["0x5fd8c710","0x66","0x72"],"storage":null},{"op":"JUMPDEST","memory":null,"memSize":96,"stack":["0x5fd8c710","0x66"],"storage":null},{"op":"PUSH1","memory":null,"memSize":96,"stack":["0x5fd8c710","0x66"],"storage":null},{"op":"DUP1","memory":null,"memSize":96,"stack":["0x5fd8c710","0x66","0x0"],"storage":null},{"op":"PUSH1","memory":null,"memSize":96,"stack":["0x5fd8c710","0x66","0x0","0x0"],"storage":null},{"op":"DUP1","memory":null,"memSize":96,"stack":["0x5fd8c710","0x66","0x0","0x0","0x0"],"storage":null},{"op":"CALLER","memory":null,"memSize":96,"stack":["0x5fd8c710","0x66","0x0","0x0","0x0","0x0"],"storage":null},{"op":"PUSH20","memory":null,"memSize":96,"stack":["0x5fd8c710","0x66","0x0","0x0","0x0","0x0","0x822607ed60d8db643d30667f59629749d1cd8af1"],"storage":null},{"op":"AND","memory":null,"memSize":96,"stack":["0x5fd8c710","0x66","0x0","0x0","0x0","0x0","0x822607ed60d8db643d30667f59629749d1cd8af1","0xffffffffffffffffffffffffffffffffffffffff"],"storage":null},{"op":"PUSH20","memory":null,"memSize":96,"stack":["0x5fd8c710","0x66","0x0","0x0","0x0","0x0","0x822607ed60d8db643d30667f59629749d1cd8af1"],"storage":null},{"op":"AND","memory":null,"memSize":96,"stack":["0x5fd8c710","0x66","0x0","0x0","0x0","0x0","0x822607ed60d8db643d30667f59629749d1cd8af1","0xffffffffffffffffffffffffffffffffffffffff"],"storage":null},{"op":"DUP2","memory":null,"memSize":96,"stack":["0x5fd8c710","0x66","0x0","0x0","0x0","0x0","0x822607ed60d8db643d30667f59629749d1cd8af1"],"storage":null},{"op":"MSTORE","memory":null,"memSize":96,"stack":["0x5fd8c710","0x66","0x0","0x0","0x0","0x0","0x822607ed60d8db643d30667f59629749d1cd8af1","0x0"],"storage":null},{"op":"PUSH1","memory":null,"memSize":96,"stack":["0x5fd8c710","0x66","0x0","0x0","0x0","0x0"],"storage":null},{"op":"ADD","memory":null,"memSize":96,"stack":["0x5fd8c710","0x66","0x0","0x0","0x0","0x0","0x20"],"storage":null},{"op":"SWAP1","memory":null,"memSize":96,"stack":["0x5fd8c710","0x66","0x0","0x0","0x0","0x20"],"storage":null},{"op":"DUP2","memory":null,"memSize":96,"stack":["0x5fd8c710","0x66","0x0","0x0","0x20","0x0"],"storage":null},{"op":"MSTORE","memory":null,"memSize":96,"stack":["0x5fd8c710","0x66","0x0","0x0","0x20","0x0","0x20"],"storage":null},{"op":"PUSH1","memory":null,"memSize":96,"stack":["0x5fd8c710","0x66","0x0","0x0","0x20"],"storage":null},{"op":"ADD","memory":null,"memSize":96,"stack":["0x5fd8c710","0x66","0x0","0x0","0x20","0x20"],"storage":null},{"op":"PUSH1","memory":null,"memSize":96,"stack":["0x5fd8c710","0x66","0x0","0x0","0x40"],"storage":null},{"op":"SHA3","memory":null,"memSize":96,"stack":["0x5fd8c710","0x66","0x0","0x0","0x40","0x0"],"storage":null},{"op":"SLOAD","memory":null,"memSize":96,"stack":["0x5fd8c710","0x66","0x0","0x0","0xbcc775d055ed2fa4d31dbee37a76bd8d0bdf61c19b7bf6b7307038dc3d63acbb"],"storage":{"0xbcc775d055ed2fa4d31dbee37a76bd8d0bdf61c19b7bf6b7307038dc3d63acbb":"0x00000000000000000000000000000000000000000000006c6b935b8bbd400000"}},{"op":"SWAP2","memory":null,"memSize":96,"stack":["0x5fd8c710","0x66","0x0","0x0","0x6c6b935b8bbd400000"],"storage":null},{"op":"POP","memory":null,"memSize":96,"stack":["0x5fd8c710","0x66","0x6c6b935b8bbd400000","0x0","0x0"],"storage":null},{"op":"CALLER","memory":null,"memSize":96,"stack":["0x5fd8c710","0x66","0x6c6b935b8bbd400000","0x0"],"storage":null},{"op":"PUSH20","memory":null,"memSize":96,"stack":["0x5fd8c710","0x66","0x6c6b935b8bbd400000","0x0","0x822607ed60d8db643d30667f59629749d1cd8af1"],"storage":null},{"op":"AND","memory":null,"memSize":96,"stack":["0x5fd8c710","0x66","0x6c6b935b8bbd400000","0x0","0x822607ed60d8db643d30667f59629749d1cd8af1","0xffffffffffffffffffffffffffffffffffffffff"],"storage":null},{"op":"DUP3","memory":null,"memSize":96,"stack":["0x5fd8c710","0x66","0x6c6b935b8bbd400000","0x0","0x822607ed60d8db643d30667f59629749d1cd8af1"],"storage":null},{"op":"PUSH1","memory":null,"memSize":96,"stack":["0x5fd8c710","0x66","0x6c6b935b8bbd400000","0x0","0x822607ed60d8db643d30667f59629749d1cd8af1","0x6c6b935b8bbd400000"],"storage":null},{"op":"MLOAD","memory":null,"memSize":96,"stack":["0x5fd8c710","0x66","0x6c6b935b8bbd400000","0x0","0x822607ed60d8db643d30667f59629749d1cd8af1","0x6c6b935b8bbd400000","0x40"],"storage":null},{"op":"DUP1","memory":null,"memSize":96,"stack":["0x5fd8c710","0x66","0x6c6b935b8bbd400000","0x0","0x822607ed60d8db643d30667f59629749d1cd8af1","0x6c6b935b8bbd400000","0x80"],"storage":null},{"op":"PUSH1","memory":null,"memSize":96,"stack":["0x5fd8c710","0x66","0x6c6b935b8bbd400000","0x0","0x822607ed60d8db643d30667f59629749d1cd8af1","0x6c6b935b8bbd400000","0x80","0x80"],"storage":null},{"op":"ADD","memory":null,"memSize":96,"stack":["0x5fd8c710","0x66","0x6c6b935b8bbd400000","0x0","0x822607ed60d8db643d30667f59629749d1cd8af1","0x6c6b935b8bbd400000","0x80","0x80","0x20"],"storage":null},{"op":"SWAP1","memory":null,"memSize":96,"stack":["0x5fd8c710","0x66","0x6c6b935b8bbd400000","0x0","0x822607ed60d8db643d30667f59629749d1cd8af1","0x6c6b935b8bbd400000","0x80","0xa0"],"storage":null},{"op":"POP","memory":null,"memSize":96,"stack":["0x5fd8c710","0x66","0x6c6b935b8bbd400000","0x0","0x822607ed60d8db643d30667f59629749d1cd8af1","0x6c6b935b8bbd400000","0xa0","0x80"],"storage":null},{"op":"PUSH1","memory":null,"memSize":96,"stack":["0x5fd8c710","0x66","0x6c6b935b8bbd400000","0x0","0x822607ed60d8db643d30667f59629749d1cd8af1","0x6c6b935b8bbd400000","0xa0"],"storage":null},{"op":"PUSH1","memory":null,"memSize":96,"stack":["0x5fd8c710","0x66","0x6c6b935b8bbd400000","0x0","0x822607ed60d8db643d30667f59629749d1cd8af1","0x6c6b935b8bbd400000","0xa0","0x0"],"storage":null},{"op":"MLOAD","memory":null,"memSize":96,"stack":["0x5fd8c710","0x66","0x6c6b935b8bbd400000","0x0","0x822607ed60d8db643d30667f59629749d1cd8af1","0x6c6b935b8bbd400000","0xa0","0x0","0x40"],"storage":null},{"op":"DUP1","memory":null,"memSize":96,"stack":["0x5fd8c710","0x66","0x6c6b935b8bbd400000","0x0","0x822607ed60d8db643d30667f59629749d1cd8af1","0x6c6b935b8bbd400000","0xa0","0x0","0x80"],"storage":null},{"op":"DUP4","memory":null,"memSize":96,"stack":["0x5fd8c710","0x66","0x6c6b935b8bbd400000","0x0","0x822607ed60d8db643d30667f59629749d1cd8af1","0x6c6b935b8bbd400000","0xa0","0x0","0x80","0x80"],"storage":null},{"op":"SUB","memory":null,"memSize":96,"stack":["0x5fd8c710","0x66","0x6c6b935b8bbd400000","0x0","0x822607ed60d8db643d30667f59629749d1cd8af1","0x6c6b935b8bbd400000","0xa0","0x0","0x80","0x80","0xa0"],"storage":null},{"op":"DUP2","memory":null,"memSize":96,"stack":["0x5fd8c710","0x66","0x6c6b935b8bbd400000","0x0","0x822607ed60d8db643d30667f59629749d1cd8af1","0x6c6b935b8bbd400000","0xa0","0x0","0x80","0x20"],"storage":null},{"op":"DUP6","memory":null,"memSize":96,"stack":["0x5fd8c710","0x66","0x6c6b935b8bbd400000","0x0","0x822607ed60d8db643d30667f59629749d1cd8af1","0x6c6b935b8bbd400000","0xa0","0x0","0x80","0x20","0x80"],"storage":null},{"op":"DUP8","memory":null,"memSize":96,"stack":["0x5fd8c710","0x66","0x6c6b935b8bbd400000","0x0","0x822607ed60d8db643d30667f59629749d1cd8af1","0x6c6b935b8bbd400000","0xa0","0x0","0x80","0x20","0x80","0x6c6b935b8bbd400000"],"storage":null},{"op":"GAS","memory":null,"memSize":96,"stack":["0x5fd8c710","0x66","0x6c6b935b8bbd400000","0x0","0x822607ed60d8db643d30667f59629749d1cd8af1","0x6c6b935b8bbd400000","0xa0","0x0","0x80","0x20","0x80","0x6c6b935b8bbd400000","0x822607ed60d8db643d30667f59629749d1cd8af1"],"storage":null},{"op":"CALL","memory":null,"memSize":160,"stack":["0x5fd8c710","0x66","0x6c6b935b8bbd400000","0x0","0x822607ed60d8db643d30667f59629749d1cd8af1","0x6c6b935b8bbd400000","0xa0","0x0","0x80","0x20","0x80","0x6c6b935b8bbd400000","0x822607ed60d8db643d30667f59629749d1cd8af1","0x310f"],"storage":null},{"op":"SWAP3","memory":null,"memSize":160,"stack":["0x5fd8c710","0x66","0x6c6b935b8bbd400000","0x0","0x822607ed60d8db643d30667f59629749d1cd8af1","0x6c6b935b8bbd400000","0xa0","0x1"],"storage":null},{"op":"POP","memory":null,"memSize":160,"stack":["0x5fd8c710","0x66","0x6c6b935b8bbd400000","0x0","0x1","0x6c6b935b8bbd400000","0xa0","0x822607ed60d8db643d30667f59629749d1cd8af1"],"storage":null},{"op":"POP","memory":null,"memSize":160,"stack":["0x5fd8c710","0x66","0x6c6b935b8bbd400000","0x0","0x1","0x6c6b935b8bbd400000","0xa0"],"storage":null},{"op":"POP","memory":null,"memSize":160,"stack":["0x5fd8c710","0x66","0x6c6b935b8bbd400000","0x0","0x1","0x6c6b935b8bbd400000"],"storage":null},{"op":"SWAP1","memory":null,"memSize":160,"stack":["0x5fd8c710","0x66","0x6c6b935b8bbd400000","0x0","0x1"],"storage":null},{"op":"POP","memory":null,"memSize":160,"stack":["0x5fd8c710","0x66","0x6c6b935b8bbd400000","0x1","0x0"],"storage":null},{"op":"DUP1","memory":null,"memSize":160,"stack":["0x5fd8c710","0x66","0x6c6b935b8bbd400000","0x1"],"storage":null},{"op":"ISZERO","memory":null,"memSize":160,"stack":["0x5fd8c710","0x66","0x6c6b935b8bbd400000","0x1","0x1"],"storage":null},{"op":"ISZERO","memory":null,"memSize":160,"stack":["0x5fd8c710","0x66","0x6c6b935b8bbd400000","0x1","0x0"],"storage":null},{"op":"PUSH2","memory":null,"memSize":160,"stack":["0x5fd8c710","0x66","0x6c6b935b8bbd400000","0x1","0x1"],"storage":null},{"op":"JUMPI","memory":null,"memSize":160,"stack":["0x5fd8c710","0x66","0x6c6b935b8bbd400000","0x1","0x1","0xf6"],"storage":null},{"op":"JUMPDEST","memory":null,"memSize":160,"stack":["0x5fd8c710","0x66","0x6c6b935b8bbd400000","0x1"],"storage":null},{"op":"PUSH1","memory":null,"memSize":160,"stack":["0x5fd8c710","0x66","0x6c6b935b8bbd400000","0x1"],"storage":null},{"op":"DUP1","memory":null,"memSize":160,"stack":["0x5fd8c710","0x66","0x6c6b935b8bbd400000","0x1","0x0"],"storage":null},{"op":"PUSH1","memory":null,"memSize":160,"stack":["0x5fd8c710","0x66","0x6c6b935b8bbd400000","0x1","0x0","0x0"],"storage":null},{"op":"CALLER","memory":null,"memSize":160,"stack":["0x5fd8c710","0x66","0x6c6b935b8bbd400000","0x1","0x0","0x0","0x0"],"storage":null},{"op":"PUSH20","memory":null,"memSize":160,"stack":["0x5fd8c710","0x66","0x6c6b935b8bbd400000","0x1","0x0","0x0","0x0","0x822607ed60d8db643d30667f59629749d1cd8af1"],"storage":null},{"op":"AND","memory":null,"memSize":160,"stack":["0x5fd8c710","0x66","0x6c6b935b8bbd400000","0x1","0x0","0x0","0x0","0x822607ed60d8db643d30667f59629749d1cd8af1","0xffffffffffffffffffffffffffffffffffffffff"],"storage":null},{"op":"PUSH20","memory":null,"memSize":160,"stack":["0x5fd8c710","0x66","0x6c6b935b8bbd400000","0x1","0x0","0x0","0x0","0x822607ed60d8db643d30667f59629749d1cd8af1"],"storage":null},{"op":"AND","memory":null,"memSize":160,"stack":["0x5fd8c710","0x66","0x6c6b935b8bbd400000","0x1","0x0","0x0","0x0","0x822607ed60d8db643d30667f59629749d1cd8af1","0xffffffffffffffffffffffffffffffffffffffff"],"storage":null},{"op":"DUP2","memory":null,"memSize":160,"stack":["0x5fd8c710","0x66","0x6c6b935b8bbd400000","0x1","0x0","0x0","0x0","0x822607ed60d8db643d30667f59629749d1cd8af1"],"storage":null},{"op":"MSTORE","memory":null,"memSize":160,"stack":["0x5fd8c710","0x66","0x6c6b935b8bbd400000","0x1","0x0","0x0","0x0","0x822607ed60d8db643d30667f59629749d1cd8af1","0x0"],"storage":null},{"op":"PUSH1","memory":null,"memSize":160,"stack":["0x5fd8c710","0x66","0x6c6b935b8bbd400000","0x1","0x0","0x0","0x0"],"storage":null},{"op":"ADD","memory":null,"memSize":160,"stack":["0x5fd8c710","0x66","0x6c6b935b8bbd400000","0x1","0x0","0x0","0x0","0x20"],"storage":null},{"op":"SWAP1","memory":null,"memSize":160,"stack":["0x5fd8c710","0x66","0x6c6b935b8bbd400000","0x1","0x0","0x0","0x20"],"storage":null},{"op":"DUP2","memory":null,"memSize":160,"stack":["0x5fd8c710","0x66","0x6c6b935b8bbd400000","0x1","0x0","0x20","0x0"],"storage":null},{"op":"MSTORE","memory":null,"memSize":160,"stack":["0x5fd8c710","0x66","0x6c6b935b8bbd400000","0x1","0x0","0x20","0x0","0x20"],"storage":null},{"op":"PUSH1","memory":null,"memSize":160,"stack":["0x5fd8c710","0x66","0x6c6b935b8bbd400000","0x1","0x0","0x20"],"storage":null},{"op":"ADD","memory":null,"memSize":160,"stack":["0x5fd8c710","0x66","0x6c6b935b8bbd400000","0x1","0x0","0x20","0x20"],"storage":null},{"op":"PUSH1","memory":null,"memSize":160,"stack":["0x5fd8c710","0x66","0x6c6b935b8bbd400000","0x1","0x0","0x40"],"storage":null},{"op":"SHA3","memory":null,"memSize":160,"stack":["0x5fd8c710","0x66","0x6c6b935b8bbd400000","0x1","0x0","0x40","0x0"],"storage":null},{"op":"DUP2","memory":null,"memSize":160,"stack":["0x5fd8c710","0x66","0x6c6b935b8bbd400000","0x1","0x0","0xbcc775d055ed2fa4d31dbee37a76bd8d0bdf61c19b7bf6b7307038dc3d63acbb"],"storage":null},{"op":"SWAP1","memory":null,"memSize":160,"stack":["0x5fd8c710","0x66","0x6c6b935b8bbd400000","0x1","0x0","0xbcc775d055ed2fa4d31dbee37a76bd8d0bdf61c19b7bf6b7307038dc3d63acbb","0x0"],"storage":null},{"op":"SSTORE","memory":null,"memSize":160,"stack":["0x5fd8c710","0x66","0x6c6b935b8bbd400000","0x1","0x0","0x0","0xbcc775d055ed2fa4d31dbee37a76bd8d0bdf61c19b7bf6b7307038dc3d63acbb"],"storage":{"0xbcc775d055ed2fa4d31dbee37a76bd8d0bdf61c19b7bf6b7307038dc3d63acbb":"0x0000000000000000000000000000000000000000000000000000000000000000"}},{"op":"POP","memory":null,"memSize":160,"stack":["0x5fd8c710","0x66","0x6c6b935b8bbd400000","0x1","0x0"],"storage":null},{"op":"POP","memory":null,"memSize":160,"stack":["0x5fd8c710","0x66","0x6c6b935b8bbd400000","0x1"],"storage":null},{"op":"POP","memory":null,"memSize":160,"stack":["0x5fd8c710","0x66","0x6c6b935b8bbd400000"],"storage":null},{"op":"JUMP","memory":null,"memSize":160,"stack":["0x5fd8c710","0x66"],"storage":null},{"op":"JUMPDEST","memory":null,"memSize":160,"stack":["0x5fd8c710"],"storage":null},{"op":"STOP","memory":null,"memSize":160,"stack":["0x5fd8c710"],"storage":null}]