[{"op":"PUSH1","memory":null,"memSize":0,"stack":[],"storage":null},{"op":"PUSH1","memory":null,"memSize":0,"stack":["0x80"],"storage":null},{"op":"MSTORE","memory":null,"memSize":96,"stack":["0x80","0x40"],"storage":null},{"op":"PUSH1","memory":null,"memSize":96,"stack":[],"storage":null},{"op":"CALLDATASIZE","memory":null,"memSize":96,"stack":["0x4"],"storage":null},{"op":"LT","memory":null,"memSize":96,"stack":["0x4","0x44"],"storage":null},{"op":"PUSH2","memory":null,"memSize":96,"stack":["0x0"],"storage":null},{"op":"JUMPI","memory":null,"memSize":96,"stack":["0x0","0x41"],"storage":null},{"op":"PUSH1","memory":null,"memSize":96,"stack":[],"storage":null},{"op":"CALLDATALOAD","memory":null,"memSize":96,"stack":["0x0"],"storage":null},{"op":"PUSH29","memory":null,"memSize":96,"stack":["0x52fba25c0000000000000000000000000b6c3d23677ec417c46e839337f4f36d"],"storage":null},{"op":"SWAP1","memory":null,"memSize":96,"stack":["0x52fba25c0000000000000000000000000b6c3d23677ec417c46e839337f4f36d","0x100000000000000000000000000000000000000000000000000000000"],"storage":null},{"op":"DIV","memory":null,"memSize":96,"stack":["0x100000000000000000000000000000000000000000000000000000000","0x52fba25c0000000000000000000000000b6c3d23677ec417c46e839337f4f36d"],"storage":null},{"op":"PUSH4","memory":null,"memSize":96,"stack":["0x52fba25c"],"storage":null},{"op":"AND","memory":null,"memSize":96,"stack":["0x52fba25c","0xffffffff"],"storage":null},{"op":"DUP1","memory":null,"memSize":96,"stack":["0x52fba25c"],"storage":null},{"op":"PUSH4","memory":null,"memSize":96,"stack":["0x52fba25c","0x52fba25c"],"storage":null},{"op":"EQ","memory":null,"memSize":96,"stack":["0x52fba25c","0x52fba25c","0x52fba25c"],"storage":null},{"op":"PUSH2","memory":null,"memSize":96,"stack":["0x52fba25c","0x1"],"storage":null},{"op":"JUMPI","memory":null,"memSize":96,"stack":["0x52fba25c","0x1","0x46"],"storage":null},{"op":"JUMPDEST","memory":null,"memSize":96,"stack":["0x52fba25c"],"storage":null},{"op":"CALLVALUE","memory":null,"memSize":96,"stack":["0x52fba25c"],"storage":null},{"op":"DUP1","memory":null,"memSize":96,"stack":["0x52fba25c","0x0"],"storage":null},{"op":"ISZERO","memory":null,"memSize":96,"stack":["0x52fba25c","0x0","0x0"],"storage":null},{"op":"PUSH2","memory":null,"memSize":96,"stack":["0x52fba25c","0x0","0x1"],"storage":null},{"op":"JUMPI","memory":null,"memSize":96,"stack":["0x52fba25c","0x0","0x1","0x52"],"storage":null},{"op":"JUMPDEST","memory":null,"memSize":96,"stack":["0x52fba25c","0x0"],"storage":null},{"op":"POP","memory":null,"memSize":96,"stack":["0x52fba25c","0x0"],"storage":null},{"op":"PUSH2","memory":null,"memSize":96,"stack":["0x52fba25c"],"storage":null},{"op":"PUSH1","memory":null,"memSize":96,"stack":["0x52fba25c","0x91"],"storage":null},{"op":"DUP1","memory":null,"memSize":96,"stack":["0x52fba25c","0x91","0x4"],"storage":null},{"op":"CALLDATASIZE","memory":null,"memSize":96,"stack":["0x52fba25c","0x91","0x4","0x4"],"storage":null},{"op":"SUB","memory":null,"memSize":96,"stack":["0x52fba25c","0x91","0x4","0x4","0x44"],"storage":null},{"op":"DUP2","memory":null,"memSize":96,"stack":["0x52fba25c","0x91","0x4","0x40"],"storage":null},{"op":"ADD","memory":null,"memSize":96,"stack":["0x52fba25c","0x91","0x4","0x40","0x4"],"storage":null},{"op":"SWAP1","memory":null,"memSize":96,"stack":["0x52fba25c","0x91","0x4","0x44"],"storage":null},{"op":"DUP1","memory":null,"memSize":96,"stack":["0x52fba25c","0x91","0x44","0x4"],"storage":null},{"op":"DUP1","memory":null,"memSize":96,"stack":["0x52fba25c","0x91","0x44","0x4","0x4"],"storage":null},{"op":"CALLDATALOAD","memory":null,"memSize":96,"stack":["0x52fba25c","0x91","0x44","0x4","0x4","0x4"],"storage":null},{"op":"PUSH20","memory":null,"memSize":96,"stack":["0x52fba25c","0x91","0x44","0x4","0x4","0xb6c3d23677ec417c46e839337f4f36da14a8f13"],"storage":null},{"op":"AND","memory":null,"memSize":96,"stack":["0x52fba25c","0x91","0x44","0x4","0x4","0xb6c3d23677ec417c46e839337f4f36da14a8f13","0xffffffffffffffffffffffffffffffffffffffff"],"storage":null},{"op":"SWAP1","memory":null,"memSize":96,"stack":["0x52fba25c","0x91","0x44","0x4","0x4","0xb6c3d23677ec417c46e839337f4f36da14a8f13"],"storage":null},{"op":"PUSH1","memory":null,"memSize":96,"stack":["0x52fba25c","0x91","0x44","0x4","0xb6c3d23677ec417c46e839337f4f36da14a8f13","0x4"],"storage":null},{"op":"ADD","memory":null,"memSize":96,"stack":["0x52fba25c","0x91","0x44","0x4","0xb6c3d23677ec417c46e839337f4f36da14a8f13","0x4","0x20"],"storage":null},{"op":"SWAP1","memory":null,"memSize":96,"stack":["0x52fba25c","0x91","0x44","0x4","0xb6c3d23677ec417c46e839337f4f36da14a8f13","0x24"],"storage":null},{"op":"SWAP3","memory":null,"memSize":96,"stack":["0x52fba25c","0x91","0x44","0x4","0x24","0xb6c3d23677ec417c46e839337f4f36da14a8f13"],"storage":null},{"op":"SWAP2","memory":null,"memSize":96,"stack":["0x52fba25c","0x91","0xb6c3d23677ec417c46e839337f4f36da14a8f13","0x4","0x24","0x44"],"storage":null},{"op":"SWAP1","memory":null,"memSize":96,"stack":["0x52fba25c","0x91","0xb6c3d23677ec417c46e839337f4f36da14a8f13","0x44","0x24","0x4"],"storage":null},{"op":"DUP1","memory":null,"memSize":96,"stack":["0x52fba25c","0x91","0xb6c3d23677ec417c46e839337f4f36da14a8f13","0x44","0x4","0x24"],"storage":null},{"op":"CALLDATALOAD","memory":null,"memSize":96,"stack":["0x52fba25c","0x91","0xb6c3d23677ec417c46e839337f4f36da14a8f13","0x44","0x4","0x24","0x24"],"storage":null},{"op":"SWAP1","memory":null,"memSize":96,"stack":["0x52fba25c","0x91","0xb6c3d23677ec417c46e839337f4f36da14a8f13","0x44","0x4","0x24","0x174876e800"],"storage":null},{"op":"PUSH1","memory":null,"memSize":96,"stack":["0x52fba25c","0x91","0xb6c3d23677ec417c46e839337f4f36da14a8f13","0x44","0x4","0x174876e800","0x24"],"storage":null},{"op":"ADD","memory":null,"memSize":96,"stack":["0x52fba25c","0x91","0xb6c3d23677ec417c46e839337f4f36da14a8f13","0x44","0x4","0x174876e800","0x24","0x20"],"storage":null},{"op":"SWAP1","memory":null,"memSize":96,"stack":["0x52fba25c","0x91","0xb6c3d23677ec417c46e839337f4f36da14a8f13","0x44","0x4","0x174876e800","0x44"],"storage":null},{"op":"SWAP3","memory":null,"memSize":96,"stack":["0x52fba25c","0x91","0xb6c3d23677ec417c46e839337f4f36da14a8f13","0x44","0x4","0x44","0x174876e800"],"storage":null},{"op":"SWAP2","memory":null,"memSize":96,"stack":["0x52fba25c","0x91","0xb6c3d23677ec417c46e839337f4f36da14a8f13","0x174876e800","0x4","0x44","0x44"],"storage":null},{"op":"SWAP1","memory":null,"memSize":96,"stack":["0x52fba25c","0x91","0xb6c3d23677ec417c46e839337f4f36da14a8f13","0x174876e800","0x44","0x44","0x4"],"storage":null},{"op":"POP","memory":null,"memSize":96,"stack":["0x52fba25c","0x91","0xb6c3d23677ec417c46e839337f4f36da14a8f13","0x174876e800","0x44","0x4","0x44"],"storage":null},{"op":"POP","memory":null,"memSize":96,"stack":["0x52fba25c","0x91","0xb6c3d23677ec417c46e839337f4f36da14a8f13","0x174876e800","0x44","0x4"],"storage":null},{"op":"POP","memory":null,"memSize":96,"stack":["0x52fba25c","0x91","0xb6c3d23677ec417c46e839337f4f36da14a8f13","0x174876e800","0x44"],"storage":null},{"op":"PUSH2","memory":null,"memSize":96,"stack":["0x52fba25c","0x91","0xb6c3d23677ec417c46e839337f4f36da14a8f13","0x174876e800"],"storage":null},{"op":"JUMP","memory":null,"memSize":96,"stack":["0x52fba25c","0x91","0xb6c3d23677ec417c46e839337f4f36da14a8f13","0x174876e800","0x93"],"storage":null},{"op":"JUMPDEST","memory":null,"memSize":96,"stack":["0x52fba25c","0x91","0xb6c3d23677ec417c46e839337f4f36da14a8f13","0x174876e800"],"storage":null},{"op":"DUP1","memory":null,"memSize":96,"stack":["0x52fba25c","0x91","0xb6c3d23677ec417c46e839337f4f36da14a8f13","0x174876e800"],"storage":null},{"op":"PUSH1","memory":null,"memSize":96,"stack":["0x52fba25c","0x91","0xb6c3d23677ec417c46e839337f4f36da14a8f13","0x174876e800","0x174876e800"],"storage":null},{"op":"GT","memory":null,"memSize":96,"stack":["0x52fba25c","0x91","0xb6c3d23677ec417c46e839337f4f36da14a8f13","0x174876e800","0x174876e800","0x0"],"storage":null},{"op":"ISZERO","memory":null,"memSize":96,"stack":["0x52fba25c","0x91","0xb6c3d23677ec417c46e839337f4f36da14a8f13","0x174876e800","0x0"],"storage":null},{"op":"DUP1","memory":null,"memSize":96,"stack":["0x52fba25c","0x91","0xb6c3d23677ec417c46e839337f4f36da14a8f13","0x174876e800","0x1"],"storage":null},{"op":"ISZERO","memory":null,"memSize":96,"stack":["0x52fba25c","0x91","0xb6c3d23677ec417c46e839337f4f36da14a8f13","0x174876e800","0x1","0x1"],"storage":null},{"op":"PUSH2","memory":null,"memSize":96,"stack":["0x52fba25c","0x91","0xb6c3d23677ec417c46e839337f4f36da14a8f13","0x174876e800","0x1","0x0"],"storage":null},{"op":"JUMPI","memory":null,"memSize":96,"stack":["0x52fba25c","0x91","0xb6c3d23677ec417c46e839337f4f36da14a8f13","0x174876e800","0x1","0x0","0xa5"],"storage":null},{"op":"POP","memory":null,"memSize":96,"stack":["0x52fba25c","0x91","0xb6c3d23677ec417c46e839337f4f36da14a8f13","0x174876e800","0x1"],"storage":null},{"op":"PUSH2","memory":null,"memSize":96,"stack":["0x52fba25c","0x91","0xb6c3d23677ec417c46e839337f4f36da14a8f13","0x174876e800"],"storage":null},{"op":"DUP2","memory":null,"memSize":96,"stack":["0x52fba25c","0x91","0xb6c3d23677ec417c46e839337f4f36da14a8f13","0x174876e800","0x3ff"],"storage":null},{"op":"LT","memory":null,"memSize":96,"stack":["0x52fba25c","0x91","0xb6c3d23677ec417c46e839337f4f36da14a8f13","0x174876e800","0x3ff","0x174876e800"],"storage":null},{"op":"JUMPDEST","memory":null,"memSize":96,"stack":["0x52fba25c","0x91","0xb6c3d23677ec417c46e839337f4f36da14a8f13","0x174876e800","0x0"],"storage":null},{"op":"ISZERO","memory":null,"memSize":96,"stack":["0x52fba25c","0x91","0xb6c3d23677ec417c46e839337f4f36da14a8f13","0x174876e800","0x0"],"storage":null},{"op":"PUSH2","memory":null,"memSize":96,"stack":["0x52fba25c","0x91","0xb6c3d23677ec417c46e839337f4f36da14a8f13","0x174876e800","0x1"],"storage":null},{"op":"JUMPI","memory":null,"memSize":96,"stack":["0x52fba25c","0x91","0xb6c3d23677ec417c46e839337f4f36da14a8f13","0x174876e800","0x1","0x173"],"storage":null},{"op":"JUMPDEST","memory":null,"memSize":96,"stack":["0x52fba25c","0x91","0xb6c3d23677ec417c46e839337f4f36da14a8f13","0x174876e800"],"storage":null},{"op":"DUP2","memory":null,"memSize":96,"stack":["0x52fba25c","0x91","0xb6c3d23677ec417c46e839337f4f36da14a8f13","0x174876e800"],"storage":null},{"op":"PUSH20","memory":null,"memSize":96,"stack":["0x52fba25c","0x91","0xb6c3d23677ec417c46e839337f4f36da14a8f13","0x174876e800","0xb6c3d23677ec417c46e839337f4f36da14a8f13"],"storage":null},{"op":"AND","memory":null,"memSize":96,"stack":["0x52fba25c","0x91","0xb6c3d23677ec417c46e839337f4f36da14a8f13","0x174876e800","0xb6c3d23677ec417c46e839337f4f36da14a8f13","0xffffffffffffffffffffffffffffffffffffffff"],"storage":null},{"op":"PUSH4","memory":null,"memSize":96,"stack":["0x52fba25c","0x91","0xb6c3d23677ec417c46e839337f4f36da14a8f13","0x174876e800","0xb6c3d23677ec417c46e839337f4f36da14a8f13"],"storage":null},{"op":"PUSH1","memory":null,"memSize":96,"stack":["0x52fba25c","0x91","0xb6c3d23677ec417c46e839337f4f36da14a8f13","0x174876e800","0xb6c3d23677ec417c46e839337f4f36da14a8f13","0x51294de7"],"storage":null},{"op":"MLOAD","memory":null,"memSize":96,"stack":["0x52fba25c","0x91","0xb6c3d23677ec417c46e839337f4f36da14a8f13","0x174876e800","0xb6c3d23677ec417c46e839337f4f36da14a8f13","0x51294de7","0x40"],"storage":null},{"op":"DUP2","memory":null,"memSize":96,"stack":["0x52fba25c","0x91","0xb6c3d23677ec417c46e839337f4f36da14a8f13","0x174876e800","0xb6c3d23677ec417c46e839337f4f36da14a8f13","0x51294de7","0x80"],"storage":null},{"op":"PUSH4","memory":null,"memSize":96,"stack":["0x52fba25c","0x91","0xb6c3d23677ec417c46e839337f4f36da14a8f13","0x174876e800","0xb6c3d23677ec417c46e839337f4f36da14a8f13","0x51294de7","0x80","0x51294de7"],"storage":null},{"op":"AND","memory":null,"memSize":96,"stack":["0x52fba25c","0x91","0xb6c3d23677ec417c46e839337f4f36da14a8f13","0x174876e800","0xb6c3d23677ec417c46e839337f4f36da14a8f13","0x51294de7","0x80","0x51294de7","0xffffffff"],"storage":null},{"op":"PUSH29","memory":null,"memSize":96,"stack":["0x52fba25c","0x91","0xb6c3d23677ec417c46e839337f4f36da14a8f13","0x174876e800","0xb6c3d23677ec417c46e839337f4f36da14a8f13","0x51294de7","0x80","0x51294de7"],"storage":null},{"op":"MUL","memory":null,"memSize":96,"stack":["0x52fba25c","0x91","0xb6c3d23677ec417c46e839337f4f36da14a8f13","0x174876e800","0xb6c3d23677ec417c46e839337f4f36da14a8f13","0x51294de7","0x80","0x51294de7","0x100000000000000000000000000000000000000000000000000000000"],"storage":null},{"op":"DUP2","memory":null,"memSize":96,"stack":["0x52fba25c","0x91","0xb6c3d23677ec417c46e839337f4f36da14a8f13","0x174876e800","0xb6c3d23677ec417c46e839337f4f36da14a8f13","0x51294de7","0x80","0x51294de700000000000000000000000000000000000000000000000000000000"],"storage":null},{"op":"MSTORE","memory":null,"memSize":160,"stack":["0x52fba25c","0x91","0xb6c3d23677ec417c46e839337f4f36da14a8f13","0x174876e800","0xb6c3d23677ec417c46e839337f4f36da14a8f13","0x51294de7","0x80","0x51294de700000000000000000000000000000000000000000000000000000000","0x80"],"storage":null},{"op":"PUSH1","memory":null,"memSize":160,"stack":["0x52fba25c","0x91","0xb6c3d23677ec417c46e839337f4f36da14a8f13","0x174876e800","0xb6c3d23677ec417c46e839337f4f36da14a8f13","0x51294de7","0x80"],"storage":null},{"op":"ADD","memory":null,"memSize":160,"stack":["0x52fba25c","0x91","0xb6c3d23677ec417c46e839337f4f36da14a8f13","0x174876e800","0xb6c3d23677ec417c46e839337f4f36da14a8f13","0x51294de7","0x80","0x4"],"storage":null},{"op":"PUSH1","memory":null,"memSize":160,"stack":["0x52fba25c","0x91","0xb6c3d23677ec417c46e839337f4f36da14a8f13","0x174876e800","0xb6c3d23677ec417c46e839337f4f36da14a8f13","0x51294de7","0x84"],"storage":null},{"op":"PUSH1","memory":null,"memSize":160,"stack":["0x52fba25c","0x91","0xb6c3d23677ec417c46e839337f4f36da14a8f13","0x174876e800","0xb6c3d23677ec417c46e839337f4f36da14a8f13","0x51294de7","0x84","0x0"],"storage":null},{"op":"MLOAD","memory":null,"memSize":160,"stack":["0x52fba25c","0x91","0xb6c3d23677ec417c46e839337f4f36da14a8f13","0x174876e800","0xb6c3d23677ec417c46e839337f4f36da14a8f13","0x51294de7","0x84","0x0","0x40"],"storage":null},{"op":"DUP1","memory":null,"memSize":160,"stack":["0x52fba25c","0x91","0xb6c3d23677ec417c46e839337f4f36da14a8f13","0x174876e800","0xb6c3d23677ec417c46e839337f4f36da14a8f13","0x51294de7","0x84","0x0","0x80"],"storage":null},{"op":"DUP4","memory":null,"memSize":160,"stack":["0x52fba25c","0x91","0xb6c3d23677ec417c46e839337f4f36da14a8f13","0x174876e800","0xb6c3d23677ec417c46e839337f4f36da14a8f13","0x51294de7","0x84","0x0","0x80","0x80"],"storage":null},{"op":"SUB","memory":null,"memSize":160,"stack":["0x52fba25c","0x91","0xb6c3d23677ec417c46e839337f4f36da14a8f13","0x174876e800","0xb6c3d23677ec417c46e839337f4f36da14a8f13","0x51294de7","0x84","0x0","0x80","0x80","0x84"],"storage":null},{"op":"DUP2","memory":null,"memSize":160,"stack":["0x52fba25c","0x91","0xb6c3d23677ec417c46e839337f4f36da14a8f13","0x174876e800","0xb6c3d23677ec417c46e839337f4f36da14a8f13","0x51294de7","0x84","0x0","0x80","0x4"],"storage":null},{"op":"PUSH1","memory":null,"memSize":160,"stack":["0x52fba25c","0x91","0xb6c3d23677ec417c46e839337f4f36da14a8f13","0x174876e800","0xb6c3d23677ec417c46e839337f4f36da14a8f13","0x51294de7","0x84","0x0","0x80","0x4","0x80"],"storage":null},{"op":"DUP8","memory":null,"memSize":160,"stack":["0x52fba25c","0x91","0xb6c3d23677ec417c46e839337f4f36da14a8f13","0x174876e800","0xb6c3d23677ec417c46e839337f4f36da14a8f13","0x51294de7","0x84","0x0","0x80","0x4","0x80","0x0"],"storage":null},{"op":"DUP1","memory":null,"memSize":160,"stack":["0x52fba25c","0x91","0xb6c3d23677ec417c46e839337f4f36da14a8f13","0x174876e800","0xb6c3d23677ec417c46e839337f4f36da14a8f13","0x51294de7","0x84","0x0","0x80","0x4","0x80","0x0","0xb6c3d23677ec417c46e839337f4f36da14a8f13"],"storage":null},{"op":"EXTCODESIZE","memory":null,"memSize":160,"stack":["0x52fba25c","0x91","0xb6c3d23677ec417c46e839337f4f36da14a8f13","0x174876e800","0xb6c3d23677ec417c46e839337f4f36da14a8f13","0x51294de7","0x84","0x0","0x80","0x4","0x80","0x0","0xb6c3d23677ec417c46e839337f4f36da14a8f13","0xb6c3d23677ec417c46e839337f4f36da14a8f13"],"storage":null},{"op":"ISZERO","memory":null,"memSize":160,"stack":["0x52fba25c","0x91","0xb6c3d23677ec417c46e839337f4f36da14a8f13","0x174876e800","0xb6c3d23677ec417c46e839337f4f36da14a8f13","0x51294de7","0x84","0x0","0x80","0x4","0x80","0x0","0xb6c3d23677ec417c46e839337f4f36da14a8f13","0x414"],"storage":null},{"op":"DUP1","memory":null,"memSize":160,"stack":["0x52fba25c","0x91","0xb6c3d23677ec417c46e839337f4f36da14a8f13","0x174876e800","0xb6c3d23677ec417c46e839337f4f36da14a8f13","0x51294de7","0x84","0x0","0x80","0x4","0x80","0x0","0xb6c3d23677ec417c46e839337f4f36da14a8f13","0x0"],"storage":null},{"op":"ISZERO","memory":null,"memSize":160,"stack":["0x52fba25c","0x91","0xb6c3d23677ec417c46e839337f4f36da14a8f13","0x174876e800","0xb6c3d23677ec417c46e839337f4f36da14a8f13","0x51294de7","0x84","0x0","0x80","0x4","0x80","0x0","0xb6c3d23677ec417c46e839337f4f36da14a8f13","0x0","0x0"],"storage":null},{"op":"PUSH2","memory":null,"memSize":160,"stack":["0x52fba25c","0x91","0xb6c3d23677ec417c46e839337f4f36da14a8f13","0x174876e800","0xb6c3d23677ec417c46e839337f4f36da14a8f13","0x51294de7","0x84","0x0","0x80","0x4","0x80","0x0","0xb6c3d23677ec417c46e839337f4f36da14a8f13","0x0","0x1"],"storage":null},{"op":"JUMPI","memory":null,"memSize":160,"stack":["0x52fba25c","0x91","0xb6c3d23677ec417c46e839337f4f36da14a8f13","0x174876e800","0xb6c3d23677ec417c46e839337f4f36da14a8f13","0x51294de7","0x84","0x0","0x80","0x4","0x80","0x0","0xb6c3d23677ec417c46e839337f4f36da14a8f13","0x0","0x1","0x1d7"],"storage":null},{"op":"JUMPDEST","memory":null,"memSize":160,"stack":["0x52fba25c","0x91","0xb6c3d23677ec417c46e839337f4f36da14a8f13","0x174876e800","0xb6c3d23677ec417c46e839337f4f36da14a8f13","0x51294de7","0x84","0x0","0x80","0x4","0x80","0x0","0xb6c3d23677ec417c46e839337f4f36da14a8f13","0x0"],"storage":null},{"op":"POP","memory":null,"memSize":160,"stack":["0x52fba25c","0x91","0xb6c3d23677ec417c46e839337f4f36da14a8f13","0x174876e800","0xb6c3d23677ec417c46e839337f4f36da14a8f13","0x51294de7","0x84","0x0","0x80","0x4","0x80","0x0","0xb6c3d23677ec417c46e839337f4f36da14a8f13","0x0"],"storage":null},{"op":"GAS","memory":null,"memSize":160,"stack":["0x52fba25c","0x91","0xb6c3d23677ec417c46e839337f4f36da14a8f13","0x174876e800","0xb6c3d23677ec417c46e839337f4f36da14a8f13","0x51294de7","0x84","0x0","0x80","0x4","0x80","0x0","0xb6c3d23677ec417c46e839337f4f36da14a8f13"],"storage":null},{"op":"CALL","memory":null,"memSize":160,"stack":["0x52fba25c","0x91","0xb6c3d23677ec417c46e839337f4f36da14a8f13","0x174876e800","0xb6c3d23677ec417c46e839337f4f36da14a8f13","0x51294de7","0x84","0x0","0x80","0x4","0x80","0x0","0xb6c3d23677ec417c46e839337f4f36da14a8f13","0x64a1"],"storage":null},{"op":"PUSH1","memory":null,"memSize":0,"stack":[],"storage":null},{"op":"PUSH1","memory":null,"memSize":0,"stack":["0x80"],"storage":null},{"op":"MSTORE","memory":null,"memSize":96,"stack":["0x80","0x40"],"storage":null},{"op":"PUSH1","memory":null,"memSize":96,"stack":[],"storage":null},{"op":"CALLDATASIZE","memory":null,"memSize":96,"stack":["0x4"],"storage":null},{"op":"LT","memory":null,"memSize":96,"stack":["0x4","0x4"],"storage":null},{"op":"PUSH2","memory":null,"memSize":96,"stack":["0x0"],"storage":null},{"op":"JUMPI","memory":null,"memSize":96,"stack":["0x0","0x83"],"storage":null},{"op":"PUSH1","memory":null,"memSize":96,"stack":[],"storage":null},{"op":"CALLDATALOAD","memory":null,"memSize":96,"stack":["0x0"],"storage":null},{"op":"PUSH29","memory":null,"memSize":96,"stack":["0x51294de700000000000000000000000000000000000000000000000000000000"],"storage":null},{"op":"SWAP1","memory":null,"memSize":96,"stack":["0x51294de700000000000000000000000000000000000000000000000000000000","0x100000000000000000000000000000000000000000000000000000000"],"storage":null},{"op":"DIV","memory":null,"memSize":96,"stack":["0x100000000000000000000000000000000000000000000000000000000","0x51294de700000000000000000000000000000000000000000000000000000000"],"storage":null},{"op":"PUSH4","memory":null,"memSize":96,"stack":["0x51294de7"],"storage":null},{"op":"AND","memory":null,"memSize":96,"stack":["0x51294de7","0xffffffff"],"storage":null},{"op":"DUP1","memory":null,"memSize":96,"stack":["0x51294de7"],"storage":null},{"op":"PUSH4","memory":null,"memSize":96,"stack":["0x51294de7","0x51294de7"],"storage":null},{"op":"EQ","memory":null,"memSize":96,"stack":["0x51294de7","0x51294de7","0x51294de7"],"storage":null},{"op":"PUSH2","memory":null,"memSize":96,"stack":["0x51294de7","0x1"],"storage":null},{"op":"JUMPI","memory":null,"memSize":96,"stack":["0x51294de7","0x1","0x88"],"storage":null},{"op":"JUMPDEST","memory":null,"memSize":96,"stack":["0x51294de7"],"storage":null},{"op":"PUSH2","memory":null,"memSize":96,"stack":["0x51294de7"],"storage":null},{"op":"PUSH2","memory":null,"memSize":96,"stack":["0x51294de7","0x90"],"storage":null},{"op":"JUMP","memory":null,"memSize":96,"stack":["0x51294de7","0x90","0x1cb"],"storage":null},{"op":"JUMPDEST","memory":null,"memSize":96,"stack":["0x51294de7","0x90"],"storage":null},{"op":"PUSH1","memory":null,"memSize":96,"stack":["0x51294de7","0x90"],"storage":null},{"op":"SLOAD","memory":null,"memSize":96,"stack":["0x51294de7","0x90","0x4"],"storage":{"0x0000000000000000000000000000000000000000000000000000000000000004":"0x0000000000000000000000000000000000000000000000000000000000000001"}},{"op":"PUSH1","memory":null,"memSize":96,"stack":["0x51294de7","0x90","0x1"],"storage":null},{"op":"SLOAD","memory":null,"memSize":96,"stack":["0x51294de7","0x90","0x1","0x3"],"storage":{"0x0000000000000000000000000000000000000000000000000000000000000003":"0x0000000000000000000000000000000000000000000000000000000000000000","0x0000000000000000000000000000000000000000000000000000000000000004":"0x0000000000000000000000000000000000000000000000000000000000000001"}},{"op":"ADD","memory":null,"memSize":96,"stack":["0x51294de7","0x90","0x1","0x0"],"storage":null},{"op":"TIMESTAMP","memory":null,"memSize":96,"stack":["0x51294de7","0x90","0x1"],"storage":null},{"op":"LT","memory":null,"memSize":96,"stack":["0x51294de7","0x90","0x1","0x628705ef"],"storage":null},{"op":"ISZERO","memory":null,"memSize":96,"stack":["0x51294de7","0x90","0x0"],"storage":null},{"op":"PUSH2","memory":null,"memSize":96,"stack":["0x51294de7","0x90","0x1"],"storage":null},{"op":"JUMPI","memory":null,"memSize":96,"stack":["0x51294de7","0x90","0x1","0x1de"],"storage":null},{"op":"JUMPDEST","memory":null,"memSize":96,"stack":["0x51294de7","0x90"],"storage":null},{"op":"PUSH1","memory":null,"memSize":96,"stack":["0x51294de7","0x90"],"storage":null},{"op":"PUSH1","memory":null,"memSize":96,"stack":["0x51294de7","0x90","0x1"],"storage":null},{"op":"SWAP1","memory":null,"memSize":96,"stack":["0x51294de7","0x90","0x1","0x0"],"storage":null},{"op":"SLOAD","memory":null,"memSize":96,"stack":["0x51294de7","0x90","0x0","0x1"],"storage":{"0x0000000000000000000000000000000000000000000000000000000000000001":"0x0000000000000000000000000000000000000000000000000000000000000000","0x0000000000000000000000000000000000000000000000000000000000000003":"0x0000000000000000000000000000000000000000000000000000000000000000","0x0000000000000000000000000000000000000000000000000000000000000004":"0x0000000000000000000000000000000000000000000000000000000000000001"}},{"op":"SWAP1","memory":null,"memSize":96,"stack":["0x51294de7","0x90","0x0","0x0"],"storage":null},{"op":"PUSH2","memory":null,"memSize":96,"stack":["0x51294de7","0x90","0x0","0x0"],"storage":null},{"op":"EXP","memory":null,"memSize":96,"stack":["0x51294de7","0x90","0x0","0x0","0x100"],"storage":null},{"op":"SWAP1","memory":null,"memSize":96,"stack":["0x51294de7","0x90","0x0","0x1"],"storage":null},{"op":"DIV","memory":null,"memSize":96,"stack":["0x51294de7","0x90","0x1","0x0"],"storage":null},{"op":"PUSH20","memory":null,"memSize":96,"stack":["0x51294de7","0x90","0x0"],"storage":null},{"op":"AND","memory":null,"memSize":96,"stack":["0x51294de7","0x90","0x0","0xffffffffffffffffffffffffffffffffffffffff"],"storage":null},{"op":"PUSH20","memory":null,"memSize":96,"stack":["0x51294de7","0x90","0x0"],"storage":null},{"op":"AND","memory":null,"memSize":96,"stack":["0x51294de7","0x90","0x0","0xffffffffffffffffffffffffffffffffffffffff"],"storage":null},{"op":"PUSH2","memory":null,"memSize":96,"stack":["0x51294de7","0x90","0x0"],"storage":null},{"op":"PUSH1","memory":null,"memSize":96,"stack":["0x51294de7","0x90","0x0","0x8fc"],"storage":null},{"op":"SLOAD","memory":null,"memSize":96,"stack":["0x51294de7","0x90","0x0","0x8fc","0x2"],"storage":{"0x0000000000000000000000000000000000000000000000000000000000000001":"0x0000000000000000000000000000000000000000000000000000000000000000","0x0000000000000000000000000000000000000000000000000000000000000002":"0x0000000000000000000000000000000000000000000000000de0b6b3a7640000","0x0000000000000000000000000000000000000000000000000000000000000003":"0x0000000000000000000000000000000000000000000000000000000000000000","0x0000000000000000000000000000000000000000000000000000000000000004":"0x0000000000000000000000000000000000000000000000000000000000000001"}},{"op":"SWAP1","memory":null,"memSize":96,"stack":["0x51294de7","0x90","0x0","0x8fc","0xde0b6b3a7640000"],"storage":null},{"op":"DUP2","memory":null,"memSize":96,"stack":["0x51294de7","0x90","0x0","0xde0b6b3a7640000","0x8fc"],"storage":null},{"op":"ISZERO","memory":null,"memSize":96,"stack":["0x51294de7","0x90","0x0","0xde0b6b3a7640000","0x8fc","0xde0b6b3a7640000"],"storage":null},{"op":"MUL","memory":null,"memSize":96,"stack":["0x51294de7","0x90","0x0","0xde0b6b3a7640000","0x8fc","0x0"],"storage":null},{"op":"SWAP1","memory":null,"memSize":96,"stack":["0x51294de7","0x90","0x0","0xde0b6b3a7640000","0x0"],"storage":null},{"op":"PUSH1","memory":null,"memSize":96,"stack":["0x51294de7","0x90","0x0","0x0","0xde0b6b3a7640000"],"storage":null},{"op":"MLOAD","memory":null,"memSize":96,"stack":["0x51294de7","0x90","0x0","0x0","0xde0b6b3a7640000","0x40"],"storage":null},{"op":"PUSH1","memory":null,"memSize":96,"stack":["0x51294de7","0x90","0x0","0x0","0xde0b6b3a7640000","0x80"],"storage":null},{"op":"PUSH1","memory":null,"memSize":96,"stack":["0x51294de7","0x90","0x0","0x0","0xde0b6b3a7640000","0x80","0x0"],"storage":null},{"op":"MLOAD","memory":null,"memSize":96,"stack":["0x51294de7","0x90","0x0","0x0","0xde0b6b3a7640000","0x80","0x0","0x40"],"storage":null},{"op":"DUP1","memory":null,"memSize":96,"stack":["0x51294de7","0x90","0x0","0x0","0xde0b6b3a7640000","0x80","0x0","0x80"],"storage":null},{"op":"DUP4","memory":null,"memSize":96,"stack":["0x51294de7","0x90","0x0","0x0","0xde0b6b3a7640000","0x80","0x0","0x80","0x80"],"storage":null},{"op":"SUB","memory":null,"memSize":96,"stack":["0x51294de7","0x90","0x0","0x0","0xde0b6b3a7640000","0x80","0x0","0x80","0x80","0x80"],"storage":null},{"op":"DUP2","memory":null,"memSize":96,"stack":["0x51294de7","0x90","0x0","0x0","0xde0b6b3a7640000","0x80","0x0","0x80","0x0"],"storage":null},{"op":"DUP6","memory":null,"memSize":96,"stack":["0x51294de7","0x90","0x0","0x0","0xde0b6b3a7640000","0x80","0x0","0x80","0x0","0x80"],"storage":null},{"op":"DUP9","memory":null,"memSize":96,"stack":["0x51294de7","0x90","0x0","0x0","0xde0b6b3a7640000","0x80","0x0","0x80","0x0","0x80","0xde0b6b3a7640000"],"storage":null},{"op":"DUP9","memory":null,"memSize":96,"stack":["0x51294de7","0x90","0x0","0x0","0xde0b6b3a7640000","0x80","0x0","0x80","0x0","0x80","0xde0b6b3a7640000","0x0"],"storage":null},{"op":"CALL","memory":null,"memSize":96,"stack":["0x51294de7","0x90","0x0","0x0","0xde0b6b3a7640000","0x80","0x0","0x80","0x0","0x80","0xde0b6b3a7640000","0x0","0x0"],"storage":null},{"op":"SWAP4","memory":null,"memSize":96,"stack":["0x51294de7","0x90","0x0","0x0","0xde0b6b3a7640000","0x80","0x0"],"storage":null},{"op":"POP","memory":null,"memSize":96,"stack":["0x51294de7","0x90","0x0","0x0","0xde0b6b3a7640000","0x80","0x0"],"storage":null},{"op":"POP","memory":null,"memSize":96,"stack":["0x51294de7","0x90","0x0","0x0","0xde0b6b3a7640000","0x80"],"storage":null},{"op":"POP","memory":null,"memSize":96,"stack":["0x51294de7","0x90","0x0","0x0","0xde0b6b3a7640000"],"storage":null},{"op":"POP","memory":null,"memSize":96,"stack":["0x51294de7","0x90","0x0","0x0"],"storage":null},{"op":"POP","memory":null,"memSize":96,"stack":["0x51294de7","0x90","0x0"],"storage":null},{"op":"PUSH1","memory":null,"memSize":96,"stack":["0x51294de7","0x90"],"storage":null},{"op":"DUP1","memory":null,"memSize":96,"stack":["0x51294de7","0x90","0x0"],"storage":null},{"op":"SWAP1","memory":null,"memSize":96,"stack":["0x51294de7","0x90","0x0","0x0"],"storage":null},{"op":"SLOAD","memory":null,"memSize":96,"stack":["0x51294de7","0x90","0x0","0x0"],"storage":{"0x0000000000000000000000000000000000000000000000000000000000000000":"0x00000000000000000000000040c08158e9dfbcef35d09219a1ddef75281fccd8","0x0000000000000000000000000000000000000000000000000000000000000001":"0x0000000000000000000000000000000000000000000000000000000000000000","0x0000000000000000000000000000000000000000000000000000000000000002":"0x0000000000000000000000000000000000000000000000000de0b6b3a7640000","0x0000000000000000000000000000000000000000000000000000000000000003":"0x0000000000000000000000000000000000000000000000000000000000000000","0x0000000000000000000000000000000000000000000000000000000000000004":"0x0000000000000000000000000000000000000000000000000000000000000001"}},{"op":"SWAP1","memory":null,"memSize":96,"stack":["0x51294de7","0x90","0x0","0x40c08158e9dfbcef35d09219a1ddef75281fccd8"],"storage":null},{"op":"PUSH2","memory":null,"memSize":96,"stack":["0x51294de7","0x90","0x40c08158e9dfbcef35d09219a1ddef75281fccd8","0x0"],"storage":null},{"op":"EXP","memory":null,"memSize":96,"stack":["0x51294de7","0x90","0x40c08158e9dfbcef35d09219a1ddef75281fccd8","0x0","0x100"],"storage":null},{"op":"SWAP1","memory":null,"memSize":96,"stack":["0x51294de7","0x90","0x40c08158e9dfbcef35d09219a1ddef75281fccd8","0x1"],"storage":null},{"op":"DIV","memory":null,"memSize":96,"stack":["0x51294de7","0x90","0x1","0x40c08158e9dfbcef35d09219a1ddef75281fccd8"],"storage":null},{"op":"PUSH20","memory":null,"memSize":96,"stack":["0x51294de7","0x90","0x40c08158e9dfbcef35d09219a1ddef75281fccd8"],"storage":null},{"op":"AND","memory":null,"memSize":96,"stack":["0x51294de7","0x90","0x40c08158e9dfbcef35d09219a1ddef75281fccd8","0xffffffffffffffffffffffffffffffffffffffff"],"storage":null},{"op":"PUSH20","memory":null,"memSize":96,"stack":["0x51294de7","0x90","0x40c08158e9dfbcef35d09219a1ddef75281fccd8"],"storage":null},{"op":"AND","memory":null,"memSize":96,"stack":["0x51294de7","0x90","0x40c08158e9dfbcef35d09219a1ddef75281fccd8","0xffffffffffffffffffffffffffffffffffffffff"],"storage":null},{"op":"PUSH2","memory":null,"memSize":96,"stack":["0x51294de7","0x90","0x40c08158e9dfbcef35d09219a1ddef75281fccd8"],"storage":null},{"op":"PUSH8","memory":null,"memSize":96,"stack":["0x51294de7","0x90","0x40c08158e9dfbcef35d09219a1ddef75281fccd8","0x8fc"],"storage":null},{"op":"ADDRESS","memory":null,"memSize":96,"stack":["0x51294de7","0x90","0x40c08158e9dfbcef35d09219a1ddef75281fccd8","0x8fc","0xde0b6b3a7640000"],"storage":null},{"op":"PUSH20","memory":null,"memSize":96,"stack":["0x51294de7","0x90","0x40c08158e9dfbcef35d09219a1ddef75281fccd8","0x8fc","0xde0b6b3a7640000","0xb6c3d23677ec417c46e839337f4f36da14a8f13"],"storage":null},{"op":"AND","memory":null,"memSize":96,"stack":["0x51294de7","0x90","0x40c08158e9dfbcef35d09219a1ddef75281fccd8","0x8fc","0xde0b6b3a7640000","0xb6c3d23677ec417c46e839337f4f36da14a8f13","0xffffffffffffffffffffffffffffffffffffffff"],"storage":null},{"op":"BALANCE","memory":null,"memSize":96,"stack":["0x51294de7","0x90","0x40c08158e9dfbcef35d09219a1ddef75281fccd8","0x8fc","0xde0b6b3a7640000","0xb6c3d23677ec417c46e839337f4f36da14a8f13"],"storage":null},{"op":"SUB","memory":null,"memSize":96,"stack":["0x51294de7","0x90","0x40c08158e9dfbcef35d09219a1ddef75281fccd8","0x8fc","0xde0b6b3a7640000","0x0"],"storage":null},{"op":"SWAP1","memory":null,"memSize":96,"stack":["0x51294de7","0x90","0x40c08158e9dfbcef35d09219a1ddef75281fccd8","0x8fc","0xfffffffffffffffffffffffffffffffffffffffffffffffff21f494c589c0000"],"storage":null},{"op":"DUP2","memory":null,"memSize":96,"stack":["0x51294de7","0x90","0x40c08158e9dfbcef35d09219a1ddef75281fccd8","0xfffffffffffffffffffffffffffffffffffffffffffffffff21f494c589c0000","0x8fc"],"storage":null},{"op":"ISZERO","memory":null,"memSize":96,"stack":["0x51294de7","0x90","0x40c08158e9dfbcef35d09219a1ddef75281fccd8","0xfffffffffffffffffffffffffffffffffffffffffffffffff21f494c589c0000","0x8fc","0xfffffffffffffffffffffffffffffffffffffffffffffffff21f494c589c0000"],"storage":null},{"op":"MUL","memory":null,"memSize":96,"stack":["0x51294de7","0x90","0x40c08158e9dfbcef35d09219a1ddef75281fccd8","0xfffffffffffffffffffffffffffffffffffffffffffffffff21f494c589c0000","0x8fc","0x0"],"storage":null},{"op":"SWAP1","memory":null,"memSize":96,"stack":["0x51294de7","0x90","0x40c08158e9dfbcef35d09219a1ddef75281fccd8","0xfffffffffffffffffffffffffffffffffffffffffffffffff21f494c589c0000","0x0"],"storage":null},{"op":"PUSH1","memory":null,"memSize":96,"stack":["0x51294de7","0x90","0x40c08158e9dfbcef35d09219a1ddef75281fccd8","0x0","0xfffffffffffffffffffffffffffffffffffffffffffffffff21f494c589c0000"],"storage":null},{"op":"MLOAD","memory":null,"memSize":96,"stack":["0x51294de7","0x90","0x40c08158e9dfbcef35d09219a1ddef75281fccd8","0x0","0xfffffffffffffffffffffffffffffffffffffffffffffffff21f494c589c0000","0x40"],"storage":null},{"op":"PUSH1","memory":null,"memSize":96,"stack":["0x51294de7","0x90","0x40c08158e9dfbcef35d09219a1ddef75281fccd8","0x0","0xfffffffffffffffffffffffffffffffffffffffffffffffff21f494c589c0000","0x80"],"storage":null},{"op":"PUSH1","memory":null,"memSize":96,"stack":["0x51294de7","0x90","0x40c08158e9dfbcef35d09219a1ddef75281fccd8","0x0","0xfffffffffffffffffffffffffffffffffffffffffffffffff21f494c589c0000","0x80","0x0"],"storage":null},{"op":"MLOAD","memory":null,"memSize":96,"stack":["0x51294de7","0x90","0x40c08158e9dfbcef35d09219a1ddef75281fccd8","0x0","0xfffffffffffffffffffffffffffffffffffffffffffffffff21f494c589c0000","0x80","0x0","0x40"],"storage":null},{"op":"DUP1","memory":null,"memSize":96,"stack":["0x51294de7","0x90","0x40c08158e9dfbcef35d09219a1ddef75281fccd8","0x0","0xfffffffffffffffffffffffffffffffffffffffffffffffff21f494c589c0000","0x80","0x0","0x80"],"storage":null},{"op":"DUP4","memory":null,"memSize":96,"stack":["0x51294de7","0x90","0x40c08158e9dfbcef35d09219a1ddef75281fccd8","0x0","0xfffffffffffffffffffffffffffffffffffffffffffffffff21f494c589c0000","0x80","0x0","0x80","0x80"],"storage":null},{"op":"SUB","memory":null,"memSize":96,"stack":["0x51294de7","0x90","0x40c08158e9dfbcef35d09219a1ddef75281fccd8","0x0","0xfffffffffffffffffffffffffffffffffffffffffffffffff21f494c589c0000","0x80","0x0","0x80","0x80","0x80"],"storage":null},{"op":"DUP2","memory":null,"memSize":96,"stack":["0x51294de7","0x90","0x40c08158e9dfbcef35d09219a1ddef75281fccd8","0x0","0xfffffffffffffffffffffffffffffffffffffffffffffffff21f494c589c0000","0x80","0x0","0x80","0x0"],"storage":null},{"op":"DUP6","memory":null,"memSize":96,"stack":["0x51294de7","0x90","0x40c08158e9dfbcef35d09219a1ddef75281fccd8","0x0","0xfffffffffffffffffffffffffffffffffffffffffffffffff21f494c589c0000","0x80","0x0","0x80","0x0","0x80"],"storage":null},{"op":"DUP9","memory":null,"memSize":96,"stack":["0x51294de7","0x90","0x40c08158e9dfbcef35d09219a1ddef75281fccd8","0x0","0xfffffffffffffffffffffffffffffffffffffffffffffffff21f494c589c0000","0x80","0x0","0x80","0x0","0x80","0xfffffffffffffffffffffffffffffffffffffffffffffffff21f494c589c0000"],"storage":null},{"op":"DUP9","memory":null,"memSize":96,"stack":["0x51294de7","0x90","0x40c08158e9dfbcef35d09219a1ddef75281fccd8","0x0","0xfffffffffffffffffffffffffffffffffffffffffffffffff21f494c589c0000","0x80","0x0","0x80","0x0","0x80","0xfffffffffffffffffffffffffffffffffffffffffffffffff21f494c589c0000","0x40c08158e9dfbcef35d09219a1ddef75281fccd8"],"storage":null},{"op":"CALL","memory":null,"memSize":96,"stack":["0x51294de7","0x90","0x40c08158e9dfbcef35d09219a1ddef75281fccd8","0x0","0xfffffffffffffffffffffffffffffffffffffffffffffffff21f494c589c0000","0x80","0x0","0x80","0x0","0x80","0xfffffffffffffffffffffffffffffffffffffffffffffffff21f494c589c0000","0x40c08158e9dfbcef35d09219a1ddef75281fccd8","0x0"],"storage":null},{"op":"SWAP4","memory":null,"memSize":96,"stack":["0x51294de7","0x90","0x40c08158e9dfbcef35d09219a1ddef75281fccd8","0x0","0xfffffffffffffffffffffffffffffffffffffffffffffffff21f494c589c0000","0x80","0x0"],"storage":null},{"op":"POP","memory":null,"memSize":96,"stack":["0x51294de7","0x90","0x0","0x0","0xfffffffffffffffffffffffffffffffffffffffffffffffff21f494c589c0000","0x80","0x40c08158e9dfbcef35d09219a1ddef75281fccd8"],"storage":null},{"op":"POP","memory":null,"memSize":96,"stack":["0x51294de7","0x90","0x0","0x0","0xfffffffffffffffffffffffffffffffffffffffffffffffff21f494c589c0000","0x80"],"storage":null},{"op":"POP","memory":null,"memSize":96,"stack":["0x51294de7","0x90","0x0","0x0","0xfffffffffffffffffffffffffffffffffffffffffffffffff21f494c589c0000"],"storage":null},{"op":"POP","memory":null,"memSize":96,"stack":["0x51294de7","0x90","0x0","0x0"],"storage":null},{"op":"POP","memory":null,"memSize":96,"stack":["0x51294de7","0x90","0x0"],"storage":null},{"op":"PUSH1","memory":null,"memSize":96,"stack":["0x51294de7","0x90"],"storage":null},{"op":"PUSH1","memory":null,"memSize":96,"stack":["0x51294de7","0x90","0x0"],"storage":null},{"op":"PUSH1","memory":null,"memSize":96,"stack":["0x51294de7","0x90","0x0","0x1"],"storage":null},{"op":"PUSH2","memory":null,"memSize":96,"stack":["0x51294de7","0x90","0x0","0x1","0x0"],"storage":null},{"op":"EXP","memory":null,"memSize":96,"stack":["0x51294de7","0x90","0x0","0x1","0x0","0x100"],"storage":null},{"op":"DUP2","memory":null,"memSize":96,"stack":["0x51294de7","0x90","0x0","0x1","0x1"],"storage":null},{"op":"SLOAD","memory":null,"memSize":96,"stack":["0x51294de7","0x90","0x0","0x1","0x1","0x1"],"storage":{"0x0000000000000000000000000000000000000000000000000000000000000000":"0x00000000000000000000000040c08158e9dfbcef35d09219a1ddef75281fccd8","0x0000000000000000000000000000000000000000000000000000000000000001":"0x0000000000000000000000000000000000000000000000000000000000000000","0x0000000000000000000000000000000000000000000000000000000000000002":"0x0000000000000000000000000000000000000000000000000de0b6b3a7640000","0x0000000000000000000000000000000000000000000000000000000000000003":"0x0000000000000000000000000000000000000000000000000000000000000000","0x0000000000000000000000000000000000000000000000000000000000000004":"0x0000000000000000000000000000000000000000000000000000000000000001"}},{"op":"DUP2","memory":null,"memSize":96,"stack":["0x51294de7","0x90","0x0","0x1","0x1","0x0"],"storage":null},{"op":"PUSH20","memory":null,"memSize":96,"stack":["0x51294de7","0x90","0x0","0x1","0x1","0x0","0x1"],"storage":null},{"op":"MUL","memory":null,"memSize":96,"stack":["0x51294de7","0x90","0x0","0x1","0x1","0x0","0x1","0xffffffffffffffffffffffffffffffffffffffff"],"storage":null},{"op":"NOT","memory":null,"memSize":96,"stack":["0x51294de7","0x90","0x0","0x1","0x1","0x0","0xffffffffffffffffffffffffffffffffffffffff"],"storage":null},{"op":"AND","memory":null,"memSize":96,"stack":["0x51294de7","0x90","0x0","0x1","0x1","0x0","0xffffffffffffffffffffffff0000000000000000000000000000000000000000"],"storage":null},{"op":"SWAP1","memory":null,"memSize":96,"stack":["0x51294de7","0x90","0x0","0x1","0x1","0x0"],"storage":null},{"op":"DUP4","memory":null,"memSize":96,"stack":["0x51294de7","0x90","0x0","0x1","0x0","0x1"],"storage":null},{"op":"PUSH20","memory":null,"memSize":96,"stack":["0x51294de7","0x90","0x0","0x1","0x0","0x1","0x0"],"storage":null},{"op":"AND","memory":null,"memSize":96,"stack":["0x51294de7","0x90","0x0","0x1","0x0","0x1","0x0","0xffffffffffffffffffffffffffffffffffffffff"],"storage":null},{"op":"MUL","memory":null,"memSize":96,"stack":["0x51294de7","0x90","0x0","0x1","0x0","0x1","0x0"],"storage":null},{"op":"OR","memory":null,"memSize":96,"stack":["0x51294de7","0x90","0x0","0x1","0x0","0x0"],"storage":null},{"op":"SWAP1","memory":null,"memSize":96,"stack":["0x51294de7","0x90","0x0","0x1","0x0"],"storage":null},{"op":"SSTORE","memory":null,"memSize":96,"stack":["0x51294de7","0x90","0x0","0x0","0x1"],"storage":{"0x0000000000000000000000000000000000000000000000000000000000000000":"0x00000000000000000000000040c08158e9dfbcef35d09219a1ddef75281fccd8","0x0000000000000000000000000000000000000000000000000000000000000001":"0x0000000000000000000000000000000000000000000000000000000000000000","0x0000000000000000000000000000000000000000000000000000000000000002":"0x0000000000000000000000000000000000000000000000000de0b6b3a7640000","0x0000000000000000000000000000000000000000000000000000000000000003":"0x0000000000000000000000000000000000000000000000000000000000000000","0x0000000000000000000000000000000000000000000000000000000000000004":"0x0000000000000000000000000000000000000000000000000000000000000001"}},{"op":"POP","memory":null,"memSize":96,"stack":["0x51294de7","0x90","0x0"],"storage":null},{"op":"PUSH8","memory":null,"memSize":96,"stack":["0x51294de7","0x90"],"storage":null},{"op":"PUSH1","memory":null,"memSize":96,"stack":["0x51294de7","0x90","0xde0b6b3a7640000"],"storage":null},{"op":"DUP2","memory":null,"memSize":96,"stack":["0x51294de7","0x90","0xde0b6b3a7640000","0x2"],"storage":null},{"op":"SWAP1","memory":null,"memSize":96,"stack":["0x51294de7","0x90","0xde0b6b3a7640000","0x2","0xde0b6b3a7640000"],"storage":null},{"op":"SSTORE","memory":null,"memSize":96,"stack":["0x51294de7","0x90","0xde0b6b3a7640000","0xde0b6b3a7640000","0x2"],"storage":{"0x0000000000000000000000000000000000000000000000000000000000000000":"0x00000000000000000000000040c08158e9dfbcef35d09219a1ddef75281fccd8","0x0000000000000000000000000000000000000000000000000000000000000001":"0x0000000000000000000000000000000000000000000000000000000000000000","0x0000000000000000000000000000000000000000000000000000000000000002":"0x0000000000000000000000000000000000000000000000000de0b6b3a7640000","0x0000000000000000000000000000000000000000000000000000000000000003":"0x0000000000000000000000000000000000000000000000000000000000000000","0x0000000000000000000000000000000000000000000000000000000000000004":"0x0000000000000000000000000000000000000000000000000000000000000001"}},{"op":"POP","memory":null,"memSize":96,"stack":["0x51294de7","0x90","0xde0b6b3a7640000"],"storage":null},{"op":"PUSH1","memory":null,"memSize":96,"stack":["0x51294de7","0x90"],"storage":null},{"op":"PUSH1","memory":null,"memSize":96,"stack":["0x51294de7","0x90","0x0"],"storage":null},{"op":"DUP2","memory":null,"memSize":96,"stack":["0x51294de7","0x90","0x0","0x3"],"storage":null},{"op":"SWAP1","memory":null,"memSize":96,"stack":["0x51294de7","0x90","0x0","0x3","0x0"],"storage":null},{"op":"SSTORE","memory":null,"memSize":96,"stack":["0x51294de7","0x90","0x0","0x0","0x3"],"storage":{"0x0000000000000000000000000000000000000000000000000000000000000000":"0x00000000000000000000000040c08158e9dfbcef35d09219a1ddef75281fccd8","0x0000000000000000000000000000000000000000000000000000000000000001":"0x0000000000000000000000000000000000000000000000000000000000000000","0x0000000000000000000000000000000000000000000000000000000000000002":"0x0000000000000000000000000000000000000000000000000de0b6b3a7640000","0x0000000000000000000000000000000000000000000000000000000000000003":"0x0000000000000000000000000000000000000000000000000000000000000000","0x0000000000000000000000000000000000000000000000000000000000000004":"0x0000000000000000000000000000000000000000000000000000000000000001"}},{"op":"POP","memory":null,"memSize":96,"stack":["0x51294de7","0x90","0x0"],"storage":null},{"op":"JUMP","memory":null,"memSize":96,"stack":["0x51294de7","0x90"],"storage":null},{"op":"JUMPDEST","memory":null,"memSize":96,"stack":["0x51294de7"],"storage":null},{"op":"STOP","memory":null,"memSize":96,"stack":["0x51294de7"],"storage":null},{"op":"ISZERO","memory":null,"memSize":160,"stack":["0x52fba25c","0x91","0xb6c3d23677ec417c46e839337f4f36da14a8f13","0x174876e800","0xb6c3d23677ec417c46e839337f4f36da14a8f13","0x51294de7","0x84","0x1"],"storage":null},{"op":"DUP1","memory":null,"memSize":160,"stack":["0x52fba25c","0x91","0xb6c3d23677ec417c46e839337f4f36da14a8f13","0x174876e800","0xb6c3d23677ec417c46e839337f4f36da14a8f13","0x51294de7","0x84","0x0"],"storage":null},{"op":"ISZERO","memory":null,"memSize":160,"stack":["0x52fba25c","0x91","0xb6c3d23677ec417c46e839337f4f36da14a8f13","0x174876e800","0xb6c3d23677ec417c46e839337f4f36da14a8f13","0x51294de7","0x84","0x0","0x0"],"storage":null},{"op":"PUSH2","memory":null,"memSize":160,"stack":["0x52fba25c","0x91","0xb6c3d23677ec417c46e839337f4f36da14a8f13","0x174876e800","0xb6c3d23677ec417c46e839337f4f36da14a8f13","0x51294de7","0x84","0x0","0x1"],"storage":null},{"op":"JUMPI","memory":null,"memSize":160,"stack":["0x52fba25c","0x91","0xb6c3d23677ec417c46e839337f4f36da14a8f13","0x174876e800","0xb6c3d23677ec417c46e839337f4f36da14a8f13","0x51294de7","0x84","0x0","0x1","0x1eb"],"storage":null},{"op":"JUMPDEST","memory":null,"memSize":160,"stack":["0x52fba25c","0x91","0xb6c3d23677ec417c46e839337f4f36da14a8f13","0x174876e800","0xb6c3d23677ec417c46e839337f4f36da14a8f13","0x51294de7","0x84","0x0"],"storage":null},{"op":"POP","memory":null,"memSize":160,"stack":["0x52fba25c","0x91","0xb6c3d23677ec417c46e839337f4f36da14a8f13","0x174876e800","0xb6c3d23677ec417c46e839337f4f36da14a8f13","0x51294de7","0x84","0x0"],"storage":null},{"op":"POP","memory":null,"memSize":160,"stack":["0x52fba25c","0x91","0xb6c3d23677ec417c46e839337f4f36da14a8f13","0x174876e800","0xb6c3d23677ec417c46e839337f4f36da14a8f13","0x51294de7","0x84"],"storage":null},{"op":"POP","memory":null,"memSize":160,"stack":["0x52fba25c","0x91","0xb6c3d23677ec417c46e839337f4f36da14a8f13","0x174876e800","0xb6c3d23677ec417c46e839337f4f36da14a8f13","0x51294de7"],"storage":null},{"op":"POP","memory":null,"memSize":160,"stack":["0x52fba25c","0x91","0xb6c3d23677ec417c46e839337f4f36da14a8f13","0x174876e800","0xb6c3d23677ec417c46e839337f4f36da14a8f13"],"storage":null},{"op":"JUMPDEST","memory":null,"memSize":160,"stack":["0x52fba25c","0x91","0xb6c3d23677ec417c46e839337f4f36da14a8f13","0x174876e800"],"storage":null},{"op":"POP","memory":null,"memSize":160,"stack":["0x52fba25c","0x91","0xb6c3d23677ec417c46e839337f4f36da14a8f13","0x174876e800"],"storage":null},{"op":"POP","memory":null,"memSize":160,"stack":["0x52fba25c","0x91","0xb6c3d23677ec417c46e839337f4f36da14a8f13"],"storage":null},{"op":"JUMP","memory":null,"memSize":160,"stack":["0x52fba25c","0x91"],"storage":null},{"op":"JUMPDEST","memory":null,"memSize":160,"stack":["0x52fba25c"],"storage":null},{"op":"STOP","memory":null,"memSize":160,"stack":["0x52fba25c"],"storage":null}]